gh/__init__.py
gh/__main__.py
gh/cli.py
gh/patterns.json
gh/commands/__init__.py
gh/commands/network_scanner.py
gh/commands/vuln_scanner.py
gh/tests/typer_poc/__init__.py
gh/tests/typer_poc/goodbye.py
gh/tests/typer_poc/main.py
gambozino_hunter-1.0.9.dist-info/METADATA
gambozino_hunter-1.0.9.dist-info/WHEEL
gambozino_hunter-1.0.9.dist-info/entry_points.txt
gambozino_hunter-1.0.9.dist-info/RECORD
