Metadata-Version: 2.4
Name: gambozino-hunter
Version: 1.0.9
Summary: Network and Vulnerability scanner
Project-URL: Repository, https://github.com/ScriptK-dd13s/GambozinoHunter
Project-URL: Bug Tracker, https://github.com/ScriptK-dd13s/GambozinoHunter/issues
Author-email: Filipe Silva <pradyun@example.com>, Hugo Almeida <tzu-ping@example.com>
Maintainer-email: Filipe Silva <pradyun@example.com>
License-Expression: MIT
Keywords: cpe,cve,network,scanner,vulnerability
Classifier: Development Status :: 3 - Alpha
Classifier: Programming Language :: Python
Requires-Python: >=3.8
Requires-Dist: click==8.2.1
Requires-Dist: ipy==1.1
Requires-Dist: markdown-it-py==3.0.0
Requires-Dist: mdurl==0.1.2
Requires-Dist: nvdlib==0.8.0
Requires-Dist: pygments==2.19.1
Requires-Dist: rich==14.0.0
Requires-Dist: scapy==2.6.1
Requires-Dist: shellingham==1.5.4
Requires-Dist: typer==0.16.0
Requires-Dist: typing-extensions==4.14.0
